fsm-traffic-light/src/traffic_light.sv
module traffic_light (
    input logic clk_in,
    input logic n_rst_in,
    input logic tick_in,
    output logic red_out,
    output logic amber_out,
    output logic green_out
);


enum logic [1:0] {RED = 2'b00, RED_AMBER = 2'b01, GREEN = 2'b10, AMBER = 2'b11} state, next_state;
int tickCount;

always_ff @(posedge clk_in) begin
    if (!n_rst_in) begin
        tickCount <= 1;
        state <= RED;
    end else begin
        if (tick_in) begin
            tickCount <= tickCount + 1;
        end else begin
            tickCount <= tickCount;
        end
        if (state != next_state) begin
            tickCount <= 1;
            state <= next_state;
        end
        
    end
end

always_comb begin
    case (state)
        RED: begin
            if (tickCount == 4)
                next_state = RED_AMBER;
            else
                next_state = RED;
        end
        RED_AMBER: begin
            if (tickCount == 1) 
                next_state = GREEN;
            else
                next_state = RED_AMBER;
        end
        GREEN: begin
            if (tickCount == 4) 
                next_state = AMBER;
            else
                next_state = GREEN;
        end
        AMBER: begin
            if (tickCount == 1) 
                next_state = RED;
            else
                next_state = AMBER;
        end
        default: begin
            next_state = RED;
        end
    endcase
end

always_comb begin
    red_out = (state == RED || state == RED_AMBER);
    amber_out = (state == AMBER || state == RED_AMBER);
    green_out = (state == GREEN);
end

endmodule

fsm-traffic-light/tb/traffic_light_tb.sv
`timescale 1ns/1ps

module traffic_light_tb;

    localparam logic [1:0] RED = 2'b00, RED_AMBER = 2'b01,
                         GREEN = 2'b10, AMBER = 2'b11;

    logic clk = 0;
    logic n_rst_in = 0;
    logic tick_in = 0;
    logic red_out;
    logic amber_out;
    logic green_out;

    int passes = 0;
    int errors = 0;

    logic [1:0] expected_state;
    logic [1:0] expected_next_state;
    int expected_count;

    traffic_light dut (
        .clk_in(clk),
        .n_rst_in(n_rst_in),
        .tick_in(tick_in),
        .red_out(red_out),
        .amber_out(amber_out),
        .green_out(green_out)
    );

    always #5 clk = ~clk;

    task compute_expected_next_state();
        case (expected_state)
            RED: begin
                if (expected_count == 4)
                    expected_next_state = RED_AMBER;
                else
                    expected_next_state = RED;
            end
            RED_AMBER: begin
                if (expected_count == 1)
                    expected_next_state = GREEN;
                else
                    expected_next_state = RED_AMBER;
            end
            GREEN: begin
                if (expected_count == 4)
                    expected_next_state = AMBER;
                else
                    expected_next_state = GREEN;
            end
            AMBER: begin
                if (expected_count == 1)
                    expected_next_state = RED;
                else
                    expected_next_state = AMBER;
            end
            default: expected_next_state = RED;
        endcase
    endtask

    task step_model();
        compute_expected_next_state();
        if (tick_in) begin
            expected_count++;
        end else begin
            expected_count = expected_count;
        end

        if (expected_state != expected_next_state) begin
            expected_count = 1;
            expected_state = expected_next_state;
        end
    endtask

    task check();
        logic exp_red, exp_amber, exp_green;
        case (expected_state)
            RED: begin 
                exp_red=1; exp_amber=0; exp_green=0; 
            end
            RED_AMBER: begin 
                exp_red=1; exp_amber=1; exp_green=0; 
            end
            GREEN: begin 
                exp_red=0; exp_amber=0; exp_green=1; 
            end
            AMBER: begin 
                exp_red=0; exp_amber=1; exp_green=0; 
            end
            default: begin 
                exp_red=0; exp_amber=0; exp_green=0; 
            end
        endcase

        if (dut.state !== expected_state) begin
            errors++;
            $display("FAIL: expected state %0d, but got %0d", expected_state, dut.state);
        end else begin
            passes++;
        end

        if (red_out !== exp_red || amber_out !== exp_amber || green_out !== exp_green) begin
            errors++;
            $display("FAIL: outputs wrong for state %0d: got r=%b a=%b g=%b, expected r=%b a=%b g=%b", expected_state, red_out, amber_out, green_out, exp_red, exp_amber, exp_green);
        end else begin
            passes++;
        end
    endtask

    initial begin
        $dumpfile("traffic_light.vcd");
        $dumpvars(0, traffic_light_tb);

        n_rst_in = 0;
        tick_in  = 1;
        repeat (2) @(posedge clk);
        n_rst_in = 1;
        #1;

        if (dut.state == RED) begin
            passes++;
            $display("PASS: state is RED immediately after reset");
        end else begin
            errors++;
            $display("FAIL: expected RED after reset, but got %0d", dut.state);
        end
        expected_state = RED;
        expected_count = 1;

        repeat (30) begin
            @(posedge clk);
            step_model();
            #1;
            check();
        end

        tick_in = 0;
        repeat (3) begin
            @(posedge clk);
            step_model();
            #1;
            check();
        end
        tick_in = 1;

        repeat (10) begin
            @(posedge clk);
            step_model();
            #1;
            check();
        end

        $display("\n==== TEST SUMMARY ====");
        $display("Passed: %0d", passes);
        $display("Failed: %0d", errors);
        if (errors == 0) $display("ALL TESTS PASSED");
        else $display("SOME TESTS FAILED");
        $finish;
    end

endmodule

fsm-traffic-light/traffic_light.vcd
$date
	Mon Sep  7 19:15:19 2026
$end
$version
	Icarus Verilog
$end
$timescale
	1ps
$end
$scope module traffic_light_tb $end
$var wire 1 ! red_out $end
$var wire 1 " green_out $end
$var wire 1 # amber_out $end
$var parameter 2 $ AMBER $end
$var parameter 2 % GREEN $end
$var parameter 2 & RED $end
$var parameter 2 ' RED_AMBER $end
$var reg 1 ( clk $end
$var reg 1 ) n_rst_in $end
$var reg 1 * tick_in $end
$var integer 32 + errors [31:0] $end
$var integer 32 , expected_count [31:0] $end
$var reg 2 - expected_next_state [1:0] $end
$var reg 2 . expected_state [1:0] $end
$var integer 32 / passes [31:0] $end
$scope module dut $end
$var wire 1 ( clk_in $end
$var wire 1 ) n_rst_in $end
$var wire 1 * tick_in $end
$var reg 1 # amber_out $end
$var reg 1 " green_out $end
$var reg 2 0 next_state [1:0] $end
$var reg 1 ! red_out $end
$var reg 2 1 state [1:0] $end
$var integer 32 2 tickCount [31:0] $end
$upscope $end
$scope task check $end
$var reg 1 3 exp_amber $end
$var reg 1 4 exp_green $end
$var reg 1 5 exp_red $end
$upscope $end
$scope task compute_expected_next_state $end
$upscope $end
$scope task step_model $end
$upscope $end
$upscope $end
$enddefinitions $end
$comment Show the parameter values. $end
$dumpall
b1 '
b0 &
b10 %
b11 $
$end
#0
$dumpvars
05
04
03
b0 2
bx 1
b0 0
b0 /
b0 .
b0 -
b0 ,
b0 +
1*
0)
0(
x#
x"
x!
$end
#5000
0"
0#
1!
b0 1
b1 2
1(
#10000
0(
#15000
1)
1(
#16000
b1 ,
b1 /
#20000
0(
#25000
b10 2
b10 ,
1(
#26000
b11 /
15
#30000
0(
#35000
b11 2
b11 ,
1(
#36000
b101 /
#40000
0(
#45000
b1 0
b100 2
b100 ,
1(
#46000
b111 /
#50000
0(
#55000
1#
b10 0
b1 1
b1 2
b1 .
b1 ,
b1 -
1(
#56000
b1001 /
13
#60000
0(
#65000
1"
0#
0!
b10 1
b1 2
b10 .
b1 ,
b10 -
1(
#66000
b1011 /
14
03
05
#70000
0(
#75000
b10 2
b10 ,
1(
#76000
b1101 /
#80000
0(
#85000
b11 2
b11 ,
1(
#86000
b1111 /
#90000
0(
#95000
b11 0
b100 2
b100 ,
1(
#96000
b10001 /
#100000
0(
#105000
0"
1#
b0 0
b11 1
b1 2
b11 .
b1 ,
b11 -
1(
#106000
b10011 /
04
13
#110000
0(
#115000
0#
1!
b0 1
b1 2
b0 .
b1 ,
b0 -
1(
#116000
b10101 /
03
15
#120000
0(
#125000
b10 2
b10 ,
1(
#126000
b10111 /
#130000
0(
#135000
b11 2
b11 ,
1(
#136000
b11001 /
#140000
0(
#145000
b1 0
b100 2
b100 ,
1(
#146000
b11011 /
#150000
0(
#155000
1#
b10 0
b1 1
b1 2
b1 .
b1 ,
b1 -
1(
#156000
b11101 /
13
#160000
0(
#165000
1"
0#
0!
b10 1
b1 2
b10 .
b1 ,
b10 -
1(
#166000
b11111 /
14
03
05
#170000
0(
#175000
b10 2
b10 ,
1(
#176000
b100001 /
#180000
0(
#185000
b11 2
b11 ,
1(
#186000
b100011 /
#190000
0(
#195000
b11 0
b100 2
b100 ,
1(
#196000
b100101 /
#200000
0(
#205000
0"
1#
b0 0
b11 1
b1 2
b11 .
b1 ,
b11 -
1(
#206000
b100111 /
04
13
#210000
0(
#215000
0#
1!
b0 1
b1 2
b0 .
b1 ,
b0 -
1(
#216000
b101001 /
03
15
#220000
0(
#225000
b10 2
b10 ,
1(
#226000
b101011 /
#230000
0(
#235000
b11 2
b11 ,
1(
#236000
b101101 /
#240000
0(
#245000
b1 0
b100 2
b100 ,
1(
#246000
b101111 /
#250000
0(
#255000
1#
b10 0
b1 1
b1 2
b1 .
b1 ,
b1 -
1(
#256000
b110001 /
13
#260000
0(
#265000
1"
0#
0!
b10 1
b1 2
b10 .
b1 ,
b10 -
1(
#266000
b110011 /
14
03
05
#270000
0(
#275000
b10 2
b10 ,
1(
#276000
b110101 /
#280000
0(
#285000
b11 2
b11 ,
1(
#286000
b110111 /
#290000
0(
#295000
b11 0
b100 2
b100 ,
1(
#296000
b111001 /
#300000
0(
#305000
0"
1#
b0 0
b11 1
b1 2
b11 .
b1 ,
b11 -
1(
#306000
b111011 /
04
13
#310000
0(
#315000
0#
1!
b0 1
b1 2
b0 .
b1 ,
b0 -
1(
#316000
0*
b111101 /
03
15
#320000
0(
#325000
1(
#326000
b111111 /
#330000
0(
#335000
1(
#336000
b1000001 /
#340000
0(
#345000
1(
#346000
1*
b1000011 /
#350000
0(
#355000
b10 2
b10 ,
1(
#356000
b1000101 /
#360000
0(
#365000
b11 2
b11 ,
1(
#366000
b1000111 /
#370000
0(
#375000
b1 0
b100 2
b100 ,
1(
#376000
b1001001 /
#380000
0(
#385000
1#
b10 0
b1 1
b1 2
b1 .
b1 ,
b1 -
1(
#386000
b1001011 /
13
#390000
0(
#395000
1"
0#
0!
b10 1
b1 2
b10 .
b1 ,
b10 -
1(
#396000
b1001101 /
14
03
05
#400000
0(
#405000
b10 2
b10 ,
1(
#406000
b1001111 /
#410000
0(
#415000
b11 2
b11 ,
1(
#416000
b1010001 /
#420000
0(
#425000
b11 0
b100 2
b100 ,
1(
#426000
b1010011 /
#430000
0(
#435000
0"
1#
b0 0
b11 1
b1 2
b11 .
b1 ,
b11 -
1(
#436000
b1010101 /
04
13
#440000
0(
#445000
0#
1!
b0 1
b1 2
b0 .
b1 ,
b0 -
1(
#446000
b1010111 /
03
15
